youtube_api2/__init__.py
youtube_api2-0.1.dist-info/METADATA
youtube_api2-0.1.dist-info/WHEEL
youtube_api2-0.1.dist-info/top_level.txt
youtube_api2-0.1.dist-info/RECORD
