Metadata-Version: 2.1
Name: youtube-api2
Version: 0.1
Requires-Dist: requests
